stable/__init__.py
stable/core.py
stable/utils.py
stable/adapters/__init__.py
stable/adapters/scipy_adapter.py
stable/adapters/statsmodels_adapter.py
stable/exporters/__init__.py
stable/exporters/excel.py
stable/exporters/html.py
stable/exporters/markdown.py
stable_stats-0.1.4.dist-info/licenses/LICENSE
stable_stats-0.1.4.dist-info/METADATA
stable_stats-0.1.4.dist-info/WHEEL
stable_stats-0.1.4.dist-info/entry_points.txt
stable_stats-0.1.4.dist-info/top_level.txt
stable_stats-0.1.4.dist-info/RECORD
