Metadata-Version: 2.4
Name: stable-stats
Version: 0.1.4
Summary: A Python package for beautifying statistical outputs into clean tables
Home-page: https://github.com/Chris-R030307/StaTable
Author: Christopher Ren
Author-email: Christopher Ren <chris.ren@emory.edu>
Maintainer-email: Christopher Ren <chris.ren@emory.edu>
License: MIT License
Project-URL: Homepage, https://github.com/Chris-R030307/StaTable
Project-URL: Documentation, https://stable.readthedocs.io/
Project-URL: Repository, https://github.com/Chris-R030307/StaTable
Project-URL: Bug Tracker, https://github.com/Chris-R030307/StaTable/issues
Project-URL: Changelog, https://github.com/Chris-R030307/StaTable/blob/main/CHANGELOG.md
Keywords: statistics,scipy,statsmodels,tables,formatting,data analysis
Classifier: Development Status :: 3 - Alpha
Classifier: Intended Audience :: Science/Research
Classifier: License :: OSI Approved :: MIT License
Classifier: Operating System :: OS Independent
Classifier: Programming Language :: Python :: 3
Classifier: Programming Language :: Python :: 3.8
Classifier: Programming Language :: Python :: 3.9
Classifier: Programming Language :: Python :: 3.10
Classifier: Programming Language :: Python :: 3.11
Classifier: Programming Language :: Python :: 3.12
Classifier: Topic :: Scientific/Engineering :: Mathematics
Classifier: Topic :: Scientific/Engineering :: Information Analysis
Requires-Python: >=3.8
License-File: LICENSE
Requires-Dist: numpy>=1.19.0
Requires-Dist: pandas>=1.3.0
Requires-Dist: scipy>=1.7.0
Requires-Dist: statsmodels>=0.12.0
Requires-Dist: openpyxl>=3.0.0
Provides-Extra: dev
Requires-Dist: pytest>=6.0; extra == "dev"
Requires-Dist: pytest-cov>=2.0; extra == "dev"
Requires-Dist: black>=21.0; extra == "dev"
Requires-Dist: flake8>=3.8; extra == "dev"
Requires-Dist: mypy>=0.800; extra == "dev"
Requires-Dist: pre-commit>=2.0; extra == "dev"
Provides-Extra: docs
Requires-Dist: sphinx>=3.0; extra == "docs"
Requires-Dist: sphinx-rtd-theme>=0.5; extra == "docs"
Requires-Dist: myst-parser>=0.15; extra == "docs"
Provides-Extra: test
Requires-Dist: pytest>=6.0; extra == "test"
Requires-Dist: pytest-cov>=2.0; extra == "test"
Requires-Dist: pytest-xdist>=2.0; extra == "test"
Dynamic: author
Dynamic: home-page
Dynamic: license-file
Dynamic: requires-python
